job_lock/__init__.py
job_lock/job_lock.py
job_lock/slurm_tmpdir.py
slurm_python_utils-1.7.9.dist-info/LICENSE
slurm_python_utils-1.7.9.dist-info/METADATA
slurm_python_utils-1.7.9.dist-info/NOTICE
slurm_python_utils-1.7.9.dist-info/WHEEL
slurm_python_utils-1.7.9.dist-info/entry_points.txt
slurm_python_utils-1.7.9.dist-info/top_level.txt
slurm_python_utils-1.7.9.dist-info/RECORD
