Metadata-Version: 2.1
Name: slurm-python-utils
Version: 1.7.9
Home-page: https://github.com/hroskes/slurm-python-utils
Author: Heshy Roskes
Author-email: heshyr@gmail.com
License-File: LICENSE
License-File: NOTICE
Requires-Dist: methodtools
Requires-Dist: psutil ; sys_platform != "cygwin"
